glove_python_binary.libs/libgomp-3300acd3.so.1.0.0
glove_python_binary-0.2.0.dist-info/METADATA
glove_python_binary-0.2.0.dist-info/RECORD
glove_python_binary-0.2.0.dist-info/WHEEL
glove_python_binary-0.2.0.dist-info/top_level.txt
glove/glove_cython.cpython-36m-x86_64-linux-gnu.so
glove/__init__.py
glove/glove.py
glove/corpus.py
glove/corpus_cython.cpython-36m-x86_64-linux-gnu.so
glove/metrics/__init__.py
glove/metrics/accuracy.py
glove/metrics/accuracy_cython.cpython-36m-x86_64-linux-gnu.so
